potx/__init__.py
potx/api/__init__.py
potx/api/ocr.py
potx/api/ocr2excel.py
potx/core/OCR.py
potx/core/OfdOCR.py
potx/core/__init__.py
potx/lib/CommonUtils.py
potx/lib/Config.py
potx/lib/Const.py
potx/lib/__init__.py
potx/lib/ocr_processor.py
potx/lib/potx_exception.py
potx/lib/apig_sdk/__init__.py
potx/lib/apig_sdk/signer.py
potx/lib/enums/FileTypeEnum.py
potx/lib/enums/__init__.py
tests/__init__.py
tests/test_code/__init__.py
tests/test_code/test_init.py
tests/test_code/test_ocr.py
tests/test_code/test_ocr2excel.py
potx_cloud-0.0.8.dist-info/LICENSE
potx_cloud-0.0.8.dist-info/METADATA
potx_cloud-0.0.8.dist-info/WHEEL
potx_cloud-0.0.8.dist-info/top_level.txt
potx_cloud-0.0.8.dist-info/RECORD
