Metadata-Version: 2.1
Name: potx-cloud
Version: 0.0.8
Summary: pip install potx-cloud
Home-page: https://www.python-office.com/
Author: CoderWanFeng
Author-email: 1957875073@qq.com
License: MIT
Project-URL: Bug Tracker, https://github.com/CoderWanFeng/potx-cloud/issues
Project-URL: Documentation, https://github.com/CoderWanFeng/potx-cloud/blob/main/README.md
Project-URL: Source Code, https://github.com/CoderWanFeng/potx-cloud
Platform: any
Requires-Python: >=3.7
License-File: LICENSE
Requires-Dist: tencentcloud-sdk-python-ocr
Requires-Dist: tencentcloud-sdk-python-common
Requires-Dist: PyMuPDF
Requires-Dist: pofile
Requires-Dist: pandas
Requires-Dist: loguru
Requires-Dist: toml
Requires-Dist: huaweicloudsdkcore
Requires-Dist: huaweicloudsdkocr
